[{"__symbolic":"module","version":3,"metadata":{"SplitterComponent":{"__symbolic":"class","extends":{"__symbolic":"reference","module":"./core","name":"EJComponents"},"decorators":[{"__symbolic":"call","expression":{"__symbolic":"reference","module":"@angular/core","name":"Component"},"arguments":[{"selector":"ej-splitter","template":"<ng-content></ng-content>"}]}],"members":{"allowKeyboardNavigation_input":[{"__symbolic":"property","decorators":[{"__symbolic":"call","expression":{"__symbolic":"reference","module":"@angular/core","name":"Input"},"arguments":["allowKeyboardNavigation"]}]}],"animationSpeed_input":[{"__symbolic":"property","decorators":[{"__symbolic":"call","expression":{"__symbolic":"reference","module":"@angular/core","name":"Input"},"arguments":["animationSpeed"]}]}],"cssClass_input":[{"__symbolic":"property","decorators":[{"__symbolic":"call","expression":{"__symbolic":"reference","module":"@angular/core","name":"Input"},"arguments":["cssClass"]}]}],"enableAnimation_input":[{"__symbolic":"property","decorators":[{"__symbolic":"call","expression":{"__symbolic":"reference","module":"@angular/core","name":"Input"},"arguments":["enableAnimation"]}]}],"enableRTL_input":[{"__symbolic":"property","decorators":[{"__symbolic":"call","expression":{"__symbolic":"reference","module":"@angular/core","name":"Input"},"arguments":["enableRTL"]}]}],"expanderTemplate_input":[{"__symbolic":"property","decorators":[{"__symbolic":"call","expression":{"__symbolic":"reference","module":"@angular/core","name":"Input"},"arguments":["expanderTemplate"]}]}],"height_input":[{"__symbolic":"property","decorators":[{"__symbolic":"call","expression":{"__symbolic":"reference","module":"@angular/core","name":"Input"},"arguments":["height"]}]}],"htmlAttributes_input":[{"__symbolic":"property","decorators":[{"__symbolic":"call","expression":{"__symbolic":"reference","module":"@angular/core","name":"Input"},"arguments":["htmlAttributes"]}]}],"isResponsive_input":[{"__symbolic":"property","decorators":[{"__symbolic":"call","expression":{"__symbolic":"reference","module":"@angular/core","name":"Input"},"arguments":["isResponsive"]}]}],"orientation_input":[{"__symbolic":"property","decorators":[{"__symbolic":"call","expression":{"__symbolic":"reference","module":"@angular/core","name":"Input"},"arguments":["orientation"]}]}],"properties_input":[{"__symbolic":"property","decorators":[{"__symbolic":"call","expression":{"__symbolic":"reference","module":"@angular/core","name":"Input"},"arguments":["properties"]}]}],"width_input":[{"__symbolic":"property","decorators":[{"__symbolic":"call","expression":{"__symbolic":"reference","module":"@angular/core","name":"Input"},"arguments":["width"]}]}],"options":[{"__symbolic":"property","decorators":[{"__symbolic":"call","expression":{"__symbolic":"reference","module":"@angular/core","name":"Input"},"arguments":["options"]}]}],"beforeExpandCollapse_output":[{"__symbolic":"property","decorators":[{"__symbolic":"call","expression":{"__symbolic":"reference","module":"@angular/core","name":"Output"},"arguments":["beforeExpandCollapse"]}]}],"clickOnExpander_output":[{"__symbolic":"property","decorators":[{"__symbolic":"call","expression":{"__symbolic":"reference","module":"@angular/core","name":"Output"},"arguments":["clickOnExpander"]}]}],"create_output":[{"__symbolic":"property","decorators":[{"__symbolic":"call","expression":{"__symbolic":"reference","module":"@angular/core","name":"Output"},"arguments":["create"]}]}],"destroy_output":[{"__symbolic":"property","decorators":[{"__symbolic":"call","expression":{"__symbolic":"reference","module":"@angular/core","name":"Output"},"arguments":["destroy"]}]}],"expandCollapse_output":[{"__symbolic":"property","decorators":[{"__symbolic":"call","expression":{"__symbolic":"reference","module":"@angular/core","name":"Output"},"arguments":["expandCollapse"]}]}],"resize_output":[{"__symbolic":"property","decorators":[{"__symbolic":"call","expression":{"__symbolic":"reference","module":"@angular/core","name":"Output"},"arguments":["resize"]}]}],"__ctor__":[{"__symbolic":"constructor","parameters":[{"__symbolic":"reference","module":"@angular/core","name":"ElementRef"},{"__symbolic":"reference","module":"@angular/core","name":"ChangeDetectorRef"},{"__symbolic":"reference","module":"@angular/core","name":"IterableDiffers"},{"__symbolic":"reference","module":"@angular/core","name":"KeyValueDiffers"}]}]}},"EJ_SPLITTER_COMPONENTS":[{"__symbolic":"reference","name":"SplitterComponent"}]}},{"__symbolic":"module","version":1,"metadata":{"SplitterComponent":{"__symbolic":"class","extends":{"__symbolic":"reference","module":"./core","name":"EJComponents"},"decorators":[{"__symbolic":"call","expression":{"__symbolic":"reference","module":"@angular/core","name":"Component"},"arguments":[{"selector":"ej-splitter","template":"<ng-content></ng-content>"}]}],"members":{"allowKeyboardNavigation_input":[{"__symbolic":"property","decorators":[{"__symbolic":"call","expression":{"__symbolic":"reference","module":"@angular/core","name":"Input"},"arguments":["allowKeyboardNavigation"]}]}],"animationSpeed_input":[{"__symbolic":"property","decorators":[{"__symbolic":"call","expression":{"__symbolic":"reference","module":"@angular/core","name":"Input"},"arguments":["animationSpeed"]}]}],"cssClass_input":[{"__symbolic":"property","decorators":[{"__symbolic":"call","expression":{"__symbolic":"reference","module":"@angular/core","name":"Input"},"arguments":["cssClass"]}]}],"enableAnimation_input":[{"__symbolic":"property","decorators":[{"__symbolic":"call","expression":{"__symbolic":"reference","module":"@angular/core","name":"Input"},"arguments":["enableAnimation"]}]}],"enableRTL_input":[{"__symbolic":"property","decorators":[{"__symbolic":"call","expression":{"__symbolic":"reference","module":"@angular/core","name":"Input"},"arguments":["enableRTL"]}]}],"expanderTemplate_input":[{"__symbolic":"property","decorators":[{"__symbolic":"call","expression":{"__symbolic":"reference","module":"@angular/core","name":"Input"},"arguments":["expanderTemplate"]}]}],"height_input":[{"__symbolic":"property","decorators":[{"__symbolic":"call","expression":{"__symbolic":"reference","module":"@angular/core","name":"Input"},"arguments":["height"]}]}],"htmlAttributes_input":[{"__symbolic":"property","decorators":[{"__symbolic":"call","expression":{"__symbolic":"reference","module":"@angular/core","name":"Input"},"arguments":["htmlAttributes"]}]}],"isResponsive_input":[{"__symbolic":"property","decorators":[{"__symbolic":"call","expression":{"__symbolic":"reference","module":"@angular/core","name":"Input"},"arguments":["isResponsive"]}]}],"orientation_input":[{"__symbolic":"property","decorators":[{"__symbolic":"call","expression":{"__symbolic":"reference","module":"@angular/core","name":"Input"},"arguments":["orientation"]}]}],"properties_input":[{"__symbolic":"property","decorators":[{"__symbolic":"call","expression":{"__symbolic":"reference","module":"@angular/core","name":"Input"},"arguments":["properties"]}]}],"width_input":[{"__symbolic":"property","decorators":[{"__symbolic":"call","expression":{"__symbolic":"reference","module":"@angular/core","name":"Input"},"arguments":["width"]}]}],"options":[{"__symbolic":"property","decorators":[{"__symbolic":"call","expression":{"__symbolic":"reference","module":"@angular/core","name":"Input"},"arguments":["options"]}]}],"beforeExpandCollapse_output":[{"__symbolic":"property","decorators":[{"__symbolic":"call","expression":{"__symbolic":"reference","module":"@angular/core","name":"Output"},"arguments":["beforeExpandCollapse"]}]}],"clickOnExpander_output":[{"__symbolic":"property","decorators":[{"__symbolic":"call","expression":{"__symbolic":"reference","module":"@angular/core","name":"Output"},"arguments":["clickOnExpander"]}]}],"create_output":[{"__symbolic":"property","decorators":[{"__symbolic":"call","expression":{"__symbolic":"reference","module":"@angular/core","name":"Output"},"arguments":["create"]}]}],"destroy_output":[{"__symbolic":"property","decorators":[{"__symbolic":"call","expression":{"__symbolic":"reference","module":"@angular/core","name":"Output"},"arguments":["destroy"]}]}],"expandCollapse_output":[{"__symbolic":"property","decorators":[{"__symbolic":"call","expression":{"__symbolic":"reference","module":"@angular/core","name":"Output"},"arguments":["expandCollapse"]}]}],"resize_output":[{"__symbolic":"property","decorators":[{"__symbolic":"call","expression":{"__symbolic":"reference","module":"@angular/core","name":"Output"},"arguments":["resize"]}]}],"__ctor__":[{"__symbolic":"constructor","parameters":[{"__symbolic":"reference","module":"@angular/core","name":"ElementRef"},{"__symbolic":"reference","module":"@angular/core","name":"ChangeDetectorRef"},{"__symbolic":"reference","module":"@angular/core","name":"IterableDiffers"},{"__symbolic":"reference","module":"@angular/core","name":"KeyValueDiffers"}]}]}},"EJ_SPLITTER_COMPONENTS":[{"__symbolic":"reference","name":"SplitterComponent"}]}}]